chaosinstana/__init__.py
chaosinstana/api.py
chaosinstana/types.py
chaosinstana/events/__init__.py
chaosinstana/events/probes.py
chaostoolkit_instana-0.1.0.dist-info/LICENSE
chaostoolkit_instana-0.1.0.dist-info/METADATA
chaostoolkit_instana-0.1.0.dist-info/WHEEL
chaostoolkit_instana-0.1.0.dist-info/top_level.txt
chaostoolkit_instana-0.1.0.dist-info/RECORD
