Metadata-Version: 2.1
Name: chaostoolkit-instana
Version: 0.1.0
Summary: instana intergration
Home-page: http://chaostoolkit.org
Author: chaostoolkit Team
Author-email: contact@chaostoolkit.org
License: Apache License Version 2.0
Platform: UNKNOWN
Classifier: Development Status :: 2 - Pre-Alpha
Classifier: Intended Audience :: Developers
Classifier: License :: Freely Distributable
Classifier: Operating System :: OS Independent
Classifier: License :: OSI Approved :: Apache Software License
Classifier: Programming Language :: Python
Classifier: Programming Language :: Python :: 3
Classifier: Programming Language :: Python :: 3.5
Classifier: Programming Language :: Python :: 3.6
Classifier: Programming Language :: Python :: Implementation
Classifier: Programming Language :: Python :: Implementation :: CPython
Requires-Python: >=3.5.*
Requires-Dist: chaostoolkit-lib (>=1.1.2)
Requires-Dist: logzero
Requires-Dist: dateparser
